hallcor/pulumi_projen_project_types/__init__.py
hallcor/pulumi_projen_project_types/py.typed
hallcor/pulumi_projen_project_types/_jsii/__init__.py
hallcor/pulumi_projen_project_types/_jsii/pulumi-projen-project-types@0.0.64.jsii.tgz
hallcor_pulumi_projen_project_types-0.0.64.dist-info/LICENSE
hallcor_pulumi_projen_project_types-0.0.64.dist-info/METADATA
hallcor_pulumi_projen_project_types-0.0.64.dist-info/WHEEL
hallcor_pulumi_projen_project_types-0.0.64.dist-info/top_level.txt
hallcor_pulumi_projen_project_types-0.0.64.dist-info/RECORD
