Metadata-Version: 2.1
Name: hallcor.pulumi-projen-project-types
Version: 0.0.64
Summary: @hallcor/pulumi-projen-project-types
Home-page: https://github.com/corymhall/pulumi-projen-project-types.git
Author: corymhall<43035978+corymhall@users.noreply.github.com>
License: Apache-2.0
Project-URL: Source, https://github.com/corymhall/pulumi-projen-project-types.git
Classifier: Intended Audience :: Developers
Classifier: Operating System :: OS Independent
Classifier: Programming Language :: JavaScript
Classifier: Programming Language :: Python :: 3 :: Only
Classifier: Programming Language :: Python :: 3.9
Classifier: Programming Language :: Python :: 3.10
Classifier: Programming Language :: Python :: 3.11
Classifier: Typing :: Typed
Classifier: Development Status :: 5 - Production/Stable
Classifier: License :: OSI Approved
Requires-Python: ~=3.9
License-File: LICENSE
Requires-Dist: constructs <11.0.0,>=10.4.2
Requires-Dist: jsii <2.0.0,>=1.121.0
Requires-Dist: projen <0.99.0,>=0.98.29
Requires-Dist: publication >=0.0.3
Requires-Dist: typeguard ==2.13.3
